env_checker.py
rl_worlds/__init__.py
rl_worlds/string_observation_space.py
rl_worlds/envs/__init__.py
rl_worlds/envs/grid_world.py
rl_worlds/envs/random_walk.py
rl_worlds/envs/thousand_states_random_walk.py
rl_worlds/envs/tunnel_world.py
rl_worlds/envs/windy_grid_world.py
rl_worlds-0.0.3.dist-info/licenses/LICENSE
rl_worlds-0.0.3.dist-info/METADATA
rl_worlds-0.0.3.dist-info/WHEEL
rl_worlds-0.0.3.dist-info/top_level.txt
rl_worlds-0.0.3.dist-info/RECORD
