Metadata-Version: 2.4
Name: rl_worlds
Version: 0.0.3
Author: Falguni Das Shuvo
License: MIT License
Project-URL: Repository, https://github.com/shuvoxcd01/RL-Worlds.git
Keywords: Reinforcement Learning,RL Environment,Grid World,Windy Grid World,Random Walk,Tunnel World
Requires-Python: >=3.8
License-File: LICENSE
Requires-Dist: gymnasium==1.0.0
Requires-Dist: numpy==1.24.4
Dynamic: license-file
